facttool/__init__.py
facttool/composer.py
facttool/evaluator.py
facttool/oprator.py
facttool/storage.py
facttool-0.0.1.dist-info/METADATA
facttool-0.0.1.dist-info/WHEEL
facttool-0.0.1.dist-info/top_level.txt
facttool-0.0.1.dist-info/RECORD
