Metadata-Version: 2.4
Name: facttool
Version: 0.0.1
Summary: Factor tool is a quant framework for factor research.
Author-email: ppoak <ppoak@foxmail.com>
License-Expression: MIT
Project-URL: Homepage, https://github.com/ppoak/factool
Keywords: quant,factor analysis,finance
Classifier: Programming Language :: Python :: 3
Classifier: Operating System :: OS Independent
Requires-Python: >=3.11
Requires-Dist: pandas>=2.3.2
Requires-Dist: typing>=3.10.0.0
Requires-Dist: duckdb>=1.3.2
Requires-Dist: markdown>=3.9
Requires-Dist: joblib>=1.5.2
Requires-Dist: numpy>=2.2
Requires-Dist: parquool>=0.0.11
Requires-Dist: matplotlib>=3.9
Requires-Dist: openpyxl>=3.0
Requires-Dist: quool>=7.0.11
Requires-Dist: scipy>=1.16.3
Requires-Dist: statsmodels>=0.14.5
Requires-Dist: jupyterlab>=4.4.10
Requires-Dist: plotly>=6.5.2
Requires-Dist: seaborn>=0.13.2
